core/__init__.py
core/client.py
core/crawler.py
core/parser.py
core/synthesizer.py
core/utils.py
RufusAIToolkit-0.1.0.dist-info/METADATA
RufusAIToolkit-0.1.0.dist-info/WHEEL
RufusAIToolkit-0.1.0.dist-info/entry_points.txt
RufusAIToolkit-0.1.0.dist-info/top_level.txt
RufusAIToolkit-0.1.0.dist-info/RECORD
